plone.restapi-9.15.3-py3.12-nspkg.pth
plone/restapi/__init__.py
plone/restapi/batching.py
plone/restapi/bbb.py
plone/restapi/behaviors.py
plone/restapi/blocks.py
plone/restapi/blocks_linkintegrity.py
plone/restapi/configure.zcml
plone/restapi/exceptions.py
plone/restapi/imaging.py
plone/restapi/indexers.py
plone/restapi/indexers.zcml
plone/restapi/interfaces.py
plone/restapi/meta.zcml
plone/restapi/patches.py
plone/restapi/permissions.py
plone/restapi/permissions.zcml
plone/restapi/setuphandlers.py
plone/restapi/testing.py
plone/restapi/testing.zcml
plone/restapi/cache/__init__.py
plone/restapi/cache/configure.zcml
plone/restapi/cache/paths.py
plone/restapi/controlpanels/__init__.py
plone/restapi/controlpanels/interfaces.py
plone/restapi/controlpanels/registry.py
plone/restapi/controlpanels/rules.py
plone/restapi/controlpanels/types.py
plone/restapi/demo/__init__.py
plone/restapi/demo/angular.pt
plone/restapi/demo/configure.zcml
plone/restapi/demo/demo.py
plone/restapi/deserializer/__init__.py
plone/restapi/deserializer/blocks.py
plone/restapi/deserializer/configure.zcml
plone/restapi/deserializer/dxcontent.py
plone/restapi/deserializer/dxfields.py
plone/restapi/deserializer/local_roles.py
plone/restapi/deserializer/mixins.py
plone/restapi/deserializer/relationfield.py
plone/restapi/deserializer/site.py
plone/restapi/deserializer/utils.py
plone/restapi/deserializer/controlpanels/__init__.py
plone/restapi/deserializer/controlpanels/configure.zcml
plone/restapi/deserializer/controlpanels/types.py
plone/restapi/locales/plone.restapi.pot
plone/restapi/locales/update.py
plone/restapi/locales/de/LC_MESSAGES/plone.restapi.mo
plone/restapi/locales/de/LC_MESSAGES/plone.restapi.po
plone/restapi/locales/es/LC_MESSAGES/plone.restapi.mo
plone/restapi/locales/es/LC_MESSAGES/plone.restapi.po
plone/restapi/locales/fr/LC_MESSAGES/plone.restapi.mo
plone/restapi/locales/fr/LC_MESSAGES/plone.restapi.po
plone/restapi/locales/pt_BR/LC_MESSAGES/plone.restapi.mo
plone_restapi-9.15.3.dist-info/METADATA
plone_restapi-9.15.3.dist-info/WHEEL
plone_restapi-9.15.3.dist-info/entry_points.txt
plone_restapi-9.15.3.dist-info/namespace_packages.txt
plone_restapi-9.15.3.dist-info/top_level.txt
plone_restapi-9.15.3.dist-info/RECORD
