Metadata-Version: 2.4
Name: plone.restapi
Version: 9.15.3
Summary: plone.restapi is a RESTful hypermedia API for Plone.
Home-page: https://github.com/plone/plone.restapi/
Author: Timo Stollenwerk (kitconcept GmbH)
Author-email: tisto@plone.org
License: gpl
Keywords: plone rest restful hypermedia api json
Classifier: Development Status :: 5 - Production/Stable
Classifier: Environment :: Web Environment
Classifier: Framework :: Plone
Classifier: Framework :: Plone :: 5.2
Classifier: Framework :: Plone :: 6.0
Classifier: Framework :: Plone :: 6.1
Classifier: Framework :: Plone :: Core
Classifier: Intended Audience :: Developers
Classifier: Operating System :: OS Independent
Classifier: Programming Language :: Python
Classifier: Programming Language :: Python :: 3.8
Classifier: Programming Language :: Python :: 3.9
Classifier: Programming Language :: Python :: 3.10
Classifier: Programming Language :: Python :: 3.11
Classifier: Programming Language :: Python :: 3.12
Classifier: Programming Language :: Python :: 3 :: Only
Classifier: Topic :: Software Development :: Libraries :: Python Modules
Requires-Python: >=3.8
Requires-Dist: setuptools
Requires-Dist: packaging
Requires-Dist: python-dateutil
Requires-Dist: plone.rest
Requires-Dist: plone.schema>=1.2.1
Requires-Dist: Products.CMFPlone>=5.2
Requires-Dist: PyJWT>=1.7.0
Requires-Dist: pytz
Provides-Extra: test
Requires-Dist: collective.MockMailHost; extra == "test"
Requires-Dist: plone.app.caching; extra == "test"
Requires-Dist: plone.app.contenttypes[test]; extra == "test"
Requires-Dist: plone.app.iterate; extra == "test"
Requires-Dist: plone.app.discussion[test]; extra == "test"
Requires-Dist: plone.app.multilingual; extra == "test"
Requires-Dist: plone.app.testing; extra == "test"
Requires-Dist: plone.app.upgrade; extra == "test"
Requires-Dist: plone.api; extra == "test"
Requires-Dist: plone.rest>=3.0.1; extra == "test"
Requires-Dist: requests; extra == "test"
Dynamic: author
Dynamic: author-email
Dynamic: classifier
Dynamic: description
Dynamic: description-content-type
Dynamic: home-page
Dynamic: keywords
Dynamic: license
Dynamic: provides-extra
Dynamic: requires-dist
Dynamic: requires-python
Dynamic: summary
